qrbsgen/__init__.py
qrbsgen/qrbs.py
qrbsgen/rules.py
qrbsgen-0.0.2.dist-info/LICENSE
qrbsgen-0.0.2.dist-info/METADATA
qrbsgen-0.0.2.dist-info/WHEEL
qrbsgen-0.0.2.dist-info/top_level.txt
qrbsgen-0.0.2.dist-info/RECORD
