Metadata-Version: 2.1
Name: qrbsgen
Version: 0.0.2
Summary: A simple Python library for encoding Quantum Rule Based Systems
Home-page: https://github.com/kvcmarshall/qrbsgen
Author: Kate Marshall
Author-email: kate.marshall@ibm.com
License: LICENSE.txt
Keywords: quantum computing,quantum rule based systems,rule based systems,expert systems,qiskit,python
Platform: UNKNOWN
Classifier: Programming Language :: Python :: 3.7
License-File: LICENSE
Requires-Dist: qiskit (>=0.36.0)
